git_stream/__init__.py
git_stream/__main__.py
git_stream/py.typed
git_stream-2.0.2.dist-info/entry_points.txt
git_stream-2.0.2.dist-info/licenses/LICENSE
git_stream-2.0.2.dist-info/WHEEL
git_stream-2.0.2.dist-info/METADATA
git_stream-2.0.2.dist-info/RECORD
